textops/__init__.py
textops/base.py
textops/ops/__init__.py
textops/ops/cast.py
textops/ops/fileops.py
textops/ops/listops.py
textops/ops/parse.py
textops/ops/recode.py
textops/ops/runops.py
textops/ops/strops.py
textops/ops/wrapops.py
python_textops3-3.2.1.dist-info/LICENSE.txt
python_textops3-3.2.1.dist-info/METADATA
python_textops3-3.2.1.dist-info/WHEEL
python_textops3-3.2.1.dist-info/eager_resources.txt
python_textops3-3.2.1.dist-info/top_level.txt
python_textops3-3.2.1.dist-info/RECORD
