Metadata-Version: 2.1
Name: python-textops3
Version: 3.2.1
Summary: Python text operations module
Home-page: https://github.com/elapouya/python-textops3
Author: Eric Lapouyade
Author-email: elapouya@gmail.com
License: LGPL 2.1
Keywords: textops
Platform: UNKNOWN
Classifier: Intended Audience :: Developers
Classifier: Development Status :: 4 - Beta
Classifier: Programming Language :: Python :: 3
Classifier: Programming Language :: Python :: 3.5
Classifier: Programming Language :: Python :: 3.6
Classifier: Programming Language :: Python :: 3.7
Classifier: Programming Language :: Python :: 3.8
Classifier: Programming Language :: Python :: 3.9
Classifier: Programming Language :: Python :: 3.10
License-File: LICENSE.txt
Requires-Dist: addicted3
Requires-Dist: python-dateutil
Requires-Dist: python-slugify
Requires-Dist: chardet
Provides-Extra: docs
Requires-Dist: Sphinx ; extra == 'docs'
Requires-Dist: sphinxcontrib-napoleon ; extra == 'docs'
